sphinxcontrib_shoebot-1.3.2-py3.7-nspkg.pth
sphinxcontrib/shoebot.py
sphinxcontrib_shoebot-1.3.2.dist-info/LICENSE
sphinxcontrib_shoebot-1.3.2.dist-info/METADATA
sphinxcontrib_shoebot-1.3.2.dist-info/WHEEL
sphinxcontrib_shoebot-1.3.2.dist-info/namespace_packages.txt
sphinxcontrib_shoebot-1.3.2.dist-info/top_level.txt
sphinxcontrib_shoebot-1.3.2.dist-info/RECORD
