Metadata-Version: 2.1
Name: sphinxcontrib-shoebot
Version: 1.3.2
Summary: Sphinx extension shoebot
Home-page: https://github.com/shoebot/shoebot/tree/readthedocs/doc/sphinxcontrib_shoebot
Author: Stuart Axon
Author-email: stuaxo2@yahoo.com
License: BSD
Platform: any
Classifier: Development Status :: 4 - Beta
Classifier: Environment :: Console
Classifier: Environment :: Web Environment
Classifier: Intended Audience :: Developers
Classifier: License :: OSI Approved :: BSD License
Classifier: Operating System :: OS Independent
Classifier: Programming Language :: Python
Classifier: Topic :: Documentation
Classifier: Topic :: Utilities
Requires-Dist: Sphinx (>=1.4.1)
Requires-Dist: pip (>=8.1.1)
